file_downloader/__init__.py
file_downloader/get_file.py
file_downloader/helpers.py
get_file-0.1.6.dist-info/LICENSE.txt
get_file-0.1.6.dist-info/METADATA
get_file-0.1.6.dist-info/WHEEL
get_file-0.1.6.dist-info/top_level.txt
get_file-0.1.6.dist-info/RECORD
