Metadata-Version: 2.1
Name: get-file
Version: 0.1.6
Summary: Download any file or files on the go!
Home-page: https://github.com/ahtesham007/get-file/
Author: Ahtesham Zaidi
Author-email: zsyedahtesham@gmail.com
License: MIT
Project-URL: Source, https://github.com/ahtesham007/get-file/
Platform: any
Classifier: Development Status :: 5 - Production/Stable
Classifier: Programming Language :: Python
License-File: LICENSE.txt
Requires-Dist: importlib-metadata ; python_version < "3.8"
Provides-Extra: testing
Requires-Dist: setuptools ; extra == 'testing'
Requires-Dist: pytest ; extra == 'testing'
Requires-Dist: pytest-cov ; extra == 'testing'
